bayesiannetworkx/__init__.py
bayesiannetworkx-0.0.7.dist-info/METADATA
bayesiannetworkx-0.0.7.dist-info/WHEEL
bayesiannetworkx-0.0.7.dist-info/RECORD
